cache_pandas/__init__.py
cache_pandas/file.py
cache_pandas/time.py
cache_pandas-1.0.0.dist-info/LICENSE
cache_pandas-1.0.0.dist-info/METADATA
cache_pandas-1.0.0.dist-info/WHEEL
cache_pandas-1.0.0.dist-info/top_level.txt
cache_pandas-1.0.0.dist-info/RECORD
